tests/py36/__init__.py
tests/py36/test_typed_objects.py
typet/__init__.py
typet/meta.py
typet/objects.py
typet/path.py
typet/types.py
typet/typing.py
typet/validation.py
typet-0.4.0.dist-info/LICENSE
typet-0.4.0.dist-info/METADATA
typet-0.4.0.dist-info/WHEEL
typet-0.4.0.dist-info/top_level.txt
typet-0.4.0.dist-info/RECORD
