Metadata-Version: 2.1
Name: typet
Version: 0.4.0
Summary: A library of types that simplify working with typed Python.
Home-page: https://github.com/contains-io/typet
Author: Melissa Nuno
Author-email: melissa@contains.io
License: MIT
Keywords: typing,schema,validation,types,annotation,PEP 483,PEP 484,PEP 526
Platform: UNKNOWN
Classifier: Development Status :: 3 - Alpha
Classifier: License :: OSI Approved :: MIT License
Classifier: Operating System :: OS Independent
Classifier: Programming Language :: Python
Classifier: Programming Language :: Python :: 3
Classifier: Programming Language :: Python :: 3.5
Classifier: Programming Language :: Python :: 3.6
Classifier: Programming Language :: Python :: 3.7
Classifier: Programming Language :: Python :: 3.8
Classifier: Programming Language :: Python :: Implementation :: PyPy
Classifier: Intended Audience :: Developers
Classifier: Topic :: Software Development
Requires-Dist: pathlib2
